pypsa/__init__.py
pypsa/_options.py
pypsa/collection.py
pypsa/common.py
pypsa/consistency.py
pypsa/constants.py
pypsa/deprecations.py
pypsa/descriptors.py
pypsa/examples.py
pypsa/geo.py
pypsa/guards.py
pypsa/networks.py
pypsa/py.typed
pypsa/type_utils.py
pypsa/version.py
pypsa/clustering/__init__.py
pypsa/clustering/spatial.py
pypsa/clustering/temporal.py
pypsa/components/__init__.py
pypsa/components/abstract.py
pypsa/components/array.py
pypsa/components/common.py
pypsa/components/components.py
pypsa/components/descriptors.py
pypsa/components/index.py
pypsa/components/legacy.py
pypsa/components/store.py
pypsa/components/transform.py
pypsa/components/types.py
pypsa/components/_types/__init__.py
pypsa/components/_types/_patch.py
pypsa/components/_types/buses.py
pypsa/components/_types/carriers.py
pypsa/components/_types/generators.py
pypsa/components/_types/global_constraints.py
pypsa/components/_types/line_types.py
pypsa/components/_types/lines.py
pypsa/components/_types/links.py
pypsa/components/_types/loads.py
pypsa/components/_types/shapes.py
pypsa/components/_types/shunt_impedances.py
pypsa/components/_types/storage_units.py
pypsa/components/_types/stores.py
pypsa/components/_types/sub_networks.py
pypsa/components/_types/transformer_types.py
pypsa/components/_types/transformers.py
pypsa/data/components.csv
pypsa/data/variables.csv
pypsa/data/component_attrs/buses.csv
pypsa/data/component_attrs/carriers.csv
pypsa/data/component_attrs/generators.csv
pypsa/data/component_attrs/global_constraints.csv
pypsa/data/component_attrs/line_types.csv
pypsa/data/component_attrs/lines.csv
pypsa/data/component_attrs/links.csv
pypsa/data/component_attrs/loads.csv
pypsa/data/component_attrs/networks.csv
pypsa/data/component_attrs/shapes.csv
pypsa/data/component_attrs/shunt_impedances.csv
pypsa/data/component_attrs/storage_units.csv
pypsa/data/component_attrs/stores.csv
pypsa/data/component_attrs/sub_networks.csv
pypsa/data/component_attrs/transformer_types.csv
pypsa-1.0.6.dist-info/licenses/LICENSE
pypsa-1.0.6.dist-info/METADATA
pypsa-1.0.6.dist-info/WHEEL
pypsa-1.0.6.dist-info/top_level.txt
pypsa-1.0.6.dist-info/RECORD
