Metadata-Version: 2.4
Name: pypsa
Version: 1.0.6
Summary: Python for Power Systems Analysis
Author-email: "PyPSA Developers, see https://docs.pypsa.org/latest/contributing/contributors.html" <t.brown@tu-berlin.de>
License: MIT License
Project-URL: Homepage, https://github.com/PyPSA/PyPSA
Project-URL: Source, https://github.com/PyPSA/PyPSA
Project-URL: Documentation, https://docs.pypsa.org
Classifier: Programming Language :: Python :: 3.11
Classifier: Programming Language :: Python :: 3.12
Classifier: Programming Language :: Python :: 3.13
Classifier: Development Status :: 5 - Production/Stable
Classifier: Environment :: Console
Classifier: Intended Audience :: Science/Research
Classifier: License :: OSI Approved :: MIT License
Classifier: Natural Language :: English
Classifier: Typing :: Typed
Classifier: Operating System :: OS Independent
Requires-Python: >=3.11
License-File: LICENSE
Requires-Dist: numpy
Requires-Dist: scipy
Requires-Dist: pandas>=0.24
Requires-Dist: xarray
Requires-Dist: netcdf4
Requires-Dist: linopy>=0.5.5
Requires-Dist: matplotlib
Requires-Dist: plotly
Requires-Dist: pydeck
Requires-Dist: seaborn
Requires-Dist: geopandas>=0.9
Requires-Dist: shapely
Requires-Dist: networkx>=2
Requires-Dist: deprecation
Requires-Dist: validators
Requires-Dist: highspy
Requires-Dist: levenshtein>=0.27.1
Provides-Extra: hdf5
Requires-Dist: tables; extra == "hdf5"
Provides-Extra: cartopy
Requires-Dist: cartopy>=0.16; extra == "cartopy"
Provides-Extra: excel
Requires-Dist: openpyxl; extra == "excel"
Requires-Dist: python-calamine; extra == "excel"
Provides-Extra: gurobipy
Requires-Dist: gurobipy; extra == "gurobipy"
Provides-Extra: cloudpath
Requires-Dist: cloudpathlib; extra == "cloudpath"
Provides-Extra: dev
Requires-Dist: pytest; extra == "dev"
Requires-Dist: pytest-cov; extra == "dev"
Requires-Dist: pytest-mpl; extra == "dev"
Requires-Dist: coverage; extra == "dev"
Requires-Dist: pypower; extra == "dev"
Requires-Dist: pandapower>=2.14.11; extra == "dev"
Requires-Dist: scikit-learn; extra == "dev"
Requires-Dist: pre-commit; extra == "dev"
Requires-Dist: ruff; extra == "dev"
Requires-Dist: mypy; extra == "dev"
Requires-Dist: jupyter>=1.1.1; extra == "dev"
Requires-Dist: typing-extensions>=4.14.0; extra == "dev"
Requires-Dist: reuse>=5.1.1; extra == "dev"
Provides-Extra: docs
Requires-Dist: mkdocs-material; extra == "docs"
Requires-Dist: mkdocs-ezlinks-plugin; extra == "docs"
Requires-Dist: mkdocs-autolinks-plugin; extra == "docs"
Requires-Dist: mkdocs-redirects; extra == "docs"
Requires-Dist: mkdocs-video; extra == "docs"
Requires-Dist: mkdocs-git-revision-date-localized-plugin; extra == "docs"
Requires-Dist: mkdocs-table-reader-plugin; extra == "docs"
Requires-Dist: mkdocstrings-python; extra == "docs"
Requires-Dist: mkdocs-jupyter; extra == "docs"
Requires-Dist: cairosvg; extra == "docs"
Requires-Dist: pillow; extra == "docs"
Requires-Dist: tsam; extra == "docs"
Requires-Dist: gurobipy; extra == "docs"
Requires-Dist: openpyxl; extra == "docs"
Requires-Dist: python-calamine; extra == "docs"
Dynamic: license-file
